{"paths":{"0":["fonts/font",0],"1":["sounds/bgm-numbercircle",2],"2":["sounds/boom-no",2],"3":["sounds/break-end",2],"4":["sounds/button",2],"5":["sounds/game-over",2],"6":["sounds/levelup",2],"7":["sounds/star-score",2],"8":["sounds/starUse",2],"9":["texture/img/bg/bg 2-4",3],"10":["texture/img/bg/bg_game",3],"11":["texture/img/bg/bg-lb",3],"12":["texture/img/food/banh my mu tat copy",3],"13":["texture/img/food/banhngotmauhong_2",3],"14":["texture/img/food/dabao_2",3],"15":["texture/img/food/hamberger_2",3],"16":["texture/img/food/mi_2",3],"17":["texture/img/food/nuoc_2",3],"18":["texture/img/other/ multiply",3],"19":["texture/img/other/3",3],"20":["texture/img/other/4",3],"21":["texture/img/other/close",3],"22":["texture/img/other/customerNeed-frame",3],"23":["texture/img/other/Gold",3],"24":["texture/img/other/hook_close",3],"25":["texture/img/other/hook_open",3],"26":["texture/img/other/hook_rope",3],"27":["texture/img/other/khay",3],"28":["texture/img/other/LG",3],"29":["texture/img/other/playbtn",3],"30":["texture/img/other/progress2",3],"31":["texture/img/other/rank",3],"32":["texture/img/other/setting",3],"33":["texture/img/other/shop",3],"34":["texture/img/other/texture_gameplay_1 copy",3],"35":["texture/img/other/tick",3],"36":["texture/img/popup/bgPopup",3],"37":["texture/img/popup/bt",3],"38":["texture/img/popup/circle",3],"39":["texture/img/popup/light",3],"40":["texture/img/popup/music",3],"41":["texture/img/popup/music2",3],"42":["texture/img/popup/NPC_3 copy",3],"43":["texture/img/popup/star-off",3],"44":["texture/img/popup/star",3],"45":["texture/img/popup/x",3],"46":["texture/img/popup/YOU FAILED",3],"47":["texture/img/popup/YOU WIN_",3],"48":["texture/img/Shop/bag",3],"49":["texture/img/Shop/bgShop",3],"50":["texture/img/Shop/btn_upgrade_gray",3],"51":["texture/img/Shop/btn_upgrade_green",3],"52":["texture/img/Shop/hook",3],"53":["texture/img/Shop/item_bagMoney",3],"54":["texture/img/Shop/item_hook",3],"55":["texture/img/Shop/money",3],"56":["texture/img/Shop/popup_0013_Rounded-Rectangle-10-copy-3",3],"57":["texture/img/Shop/texture_Shop_0",3],"58":["texture/img/Shop/time_happy",3],"59":["texture/img/Shop/time",3],"60":["texture/spines/char_1/char_1",3],"61":["texture/spines/char_2/char_3",3],"62":["texture/spines/char_3/1",3],"63":["texture/spines/char_4/char_4",3],"64":["texture/spines/char_5/char_3_skin",3],"65":["texture/spines/char_6/char_4_skin",3],"66":["texture/spines/char_7/char_5_skin",3],"67":["texture/spines/char_8/char_nu_2_skin",3],"68":["texture/spines/char_9/char_nu_2",3],"71":["prefab/food",1],"72":["prefab/Gold",1],"73":["prefab/Main",1],"74":["prefab/nPlayer",1],"75":["prefab/UI_PopUp/GameOver",1],"76":["prefab/UI_PopUp/SettingView",1],"77":["prefab/UI_PopUp/Shop/ItemHook",1],"78":["prefab/UI_PopUp/Shop/ShopView",1],"79":["texture/img/bg/bg 2-4",4,1],"80":["texture/img/bg/bg_game",4,1],"81":["texture/img/bg/bg-lb",4,1],"82":["texture/img/food/banh my mu tat copy",4,1],"83":["texture/img/food/banhngotmauhong_2",4,1],"84":["texture/img/food/dabao_2",4,1],"85":["texture/img/food/hamberger_2",4,1],"86":["texture/img/food/mi_2",4,1],"87":["texture/img/food/nuoc_2",4,1],"88":["texture/img/other/ multiply",4,1],"89":["texture/img/other/3",4,1],"90":["texture/img/other/4",4,1],"91":["texture/img/other/close",4,1],"92":["texture/img/other/customerNeed-frame",4,1],"93":["texture/img/other/Gold",4,1],"94":["texture/img/other/hook_close",4,1],"95":["texture/img/other/hook_open",4,1],"96":["texture/img/other/hook_rope",4,1],"97":["texture/img/other/khay",4,1],"98":["texture/img/other/LG",4,1],"99":["texture/img/other/playbtn",4,1],"100":["texture/img/other/progress2",4,1],"101":["texture/img/other/rank",4,1],"102":["texture/img/other/setting",4,1],"103":["texture/img/other/shop",4,1],"104":["texture/img/other/texture_gameplay_1 copy",4,1],"105":["texture/img/other/tick",4,1],"106":["texture/img/popup/bgPopup",4,1],"107":["texture/img/popup/bt",4,1],"108":["texture/img/popup/circle",4,1],"109":["texture/img/popup/light",4,1],"110":["texture/img/popup/music",4,1],"111":["texture/img/popup/music2",4,1],"112":["texture/img/popup/NPC_3 copy",4,1],"113":["texture/img/popup/star-off",4,1],"114":["texture/img/popup/star",4,1],"115":["texture/img/popup/x",4,1],"116":["texture/img/popup/YOU FAILED",4,1],"117":["texture/img/popup/YOU WIN_",4,1],"118":["texture/img/Shop/bag",4,1],"119":["texture/img/Shop/bgShop",4,1],"120":["texture/img/Shop/btn_upgrade_gray",4,1],"121":["texture/img/Shop/btn_upgrade_green",4,1],"122":["texture/img/Shop/hook",4,1],"123":["texture/img/Shop/item_bagMoney",4,1],"124":["texture/img/Shop/item_hook",4,1],"125":["texture/img/Shop/money",4,1],"126":["texture/img/Shop/popup_0013_Rounded-Rectangle-10-copy-3",4,1],"127":["texture/img/Shop/texture_Shop_0",4,1],"128":["texture/img/Shop/time_happy",4,1],"129":["texture/img/Shop/time",4,1],"130":["texture/spines/char_1/char_1.atlas",6],"131":["texture/spines/char_1/char_1",5],"132":["texture/spines/char_1/char_1",4,1],"133":["texture/spines/char_2/char_3.atlas",6],"134":["texture/spines/char_2/char_3",5],"135":["texture/spines/char_2/char_3",4,1],"136":["texture/spines/char_3/1.atlas",6],"137":["texture/spines/char_3/1",5],"138":["texture/spines/char_3/1",4,1],"139":["texture/spines/char_4/char_4.atlas",6],"140":["texture/spines/char_4/char_4",5],"141":["texture/spines/char_4/char_4",4,1],"142":["texture/spines/char_5/char_3_skin.atlas",6],"143":["texture/spines/char_5/char_3_skin",5],"144":["texture/spines/char_5/char_3_skin",4,1],"145":["texture/spines/char_6/char_4_skin.atlas",6],"146":["texture/spines/char_6/char_4_skin",5],"147":["texture/spines/char_6/char_4_skin",4,1],"148":["texture/spines/char_7/char_5_skin.atlas",6],"149":["texture/spines/char_7/char_5_skin",5],"150":["texture/spines/char_7/char_5_skin",4,1],"151":["texture/spines/char_8/char_nu_2_skin.atlas",6],"152":["texture/spines/char_8/char_nu_2_skin",5],"153":["texture/spines/char_8/char_nu_2_skin",4,1],"154":["texture/spines/char_9/char_nu_2.atlas",6],"155":["texture/spines/char_9/char_nu_2",5],"156":["texture/spines/char_9/char_nu_2",4,1]},"types":["cc.TTFFont","cc.Prefab","cc.AudioClip","cc.Texture2D","cc.SpriteFrame","sp.SkeletonData","cc.TextAsset"],"uuids":["ea0utgq4hF6p+F48JWKRMg","e4m2O9msZPQ41nCazcxZH0","57EYAQlCxJ95hm9nrZVuev","749ORqBnhHtqDqlAgAI8T4","e4WVF2DklKXpUOXQ9OJsXn","f8+dAJYwlCs7vWzxCBX0Ny","aa+u3jUItNta0I6f5mRylW","7bL403Y/xLirdKXmnfOHpr","45dpiiq+hLu6ZVQFKdpTDG","c3USaXS6dKSpSpBzvh2aqC","55+EayXjRAeLBFtbtWgFLm","eaiP+gxghJe4A9sGdPTVfH","71ZDssrlNDCYpkHhRaZ6/m","0eF+mzsPFAc4jIF9Z/j9aU","96V7SNIhBM2avdaO4Uzn2B","22ffCNxPFANrFCzd1ueYB3","a8o0VVErNAlJV5M7GZkqt7","30ioPbQMdMOa1pFtY4i9z1","52k6BKqQ9L4phyC2A2zMxD","81JPjwTGJOopDsTMeLMFJl","1afFzmyMlHBLuL4kbMhoN1","71L5MzoRFAcKlRTKTl3ixq","6cxGURKJFHyYNFwLy4F6O2","bc8LxDRfNG+p8jw7igROsa","30Hwt/3ylJUZNY0gMyg2Xn","d4VOCGrEBA8penKwQgPH8m","21ZgQBSGNJYbN7ns76vyyX","69LqU1s0pFpbvzVQfMSohS","10tT2X8CdNzKLc7mnSHRbM","30xDW0pcBGerhBMICG+xiB","14b3JJ+dVO84VuBmDwjFC6","00beHv+0JMXYYMbDihp0PC","7dZHWuw2NIvKyqnpfUESew","7bl8bmYR1BwpOcRfrX1OmI","42a/7hE1VAj5StRJCW715f","2dLOvWYOdMTbVpRxI+OB9G","2dtn0WtYZGI58xGciRRqbp","35h+H31/pAmYFrVXdTauxd","f9ms+5MMJC5bUUOTOWUW+S","63RAof9IVAOpmc8zkigAHy","4eksyrXzNGo4D3rlnOphV8","c4fXFCu0NLV72OoXNC8tNe","c94KBdrw9IoafMgw0PCeok","adIARbdVlLJobzK+wNXUqJ","96AEQZ94RN+5l+Z2K/V0E/","dbDuWKNcZMyp4nZpdUYKJa","a8HzG3QjRNR5e51z4uguB6","ec9O6ybBNKqKlb95nIXpRp","4dwtP4OBFH96zKziBZL/XZ","00QVb8XR5IMLcsGy0jxQBB","9eMo05V1tAbIWKWgGUKyHL","307bpumPRCmaFIG+MKVVen","bbZT58R1VEpIIVipnboK3m","c0ONybWI9BKbcDrC13JMdr","06FdKhyWxAjIVAK2x4TF9T","f0pK1SdolN06cOwjWCcC3s","42vgA9f6VLB6pOchQ/uUog","bdxIO2c91BGpirblIiuo8h","eabndCLQdG9LUm2Krkkan5","70luMuLXhKxZRTGfRiHY+y","368fXMS7dLBatlDlv+xdhr","c8Xlr8cudKg7F+VjeBHKV2","19SawW1sVDx7gBzS3thMXC","8fTlr8xatDuKS986gdUT6e","6cr4ExYPRAnKLRsnZTg/FW","26Fg0JPpFOq6P8UJ6zvTQq","a9ZfFDgWlHeZiD3xrxM9x6","19SWHyNoBFpozg+HrrMdSQ","cbJcvnSGtOw6BIC4nZieM0","ff2VuPSPNG1bLN5nklGvqm","ea/Zu+qUhPE4br3eL2G2hZ","2cRdGhTFZILpvq425YviXc","e377i/1HJHV7L/InKjqC5C","37+W1br+FNar7yBCvhdFI3","889yFtuWhMB6Ny4riQDhbG","1ckvnwWBhJZqrQrBBoKIxF","09ygXQodlNcZKriL+ilvnB","0cveV8UsNL+4tBUX/A3px3","baXi+YRRJNB6Cjekxr0PQm","16HIGtCoVGsoxcEA+Y2Jl+","cd/RmZyVZPRZg9Oq/n44FC","54AIoZbVtLM5CVALTVCej9","5eKsn+w89GSZHrv8G70hbE","93RPy/Q0JGPZ4Vfzy/tZWE","67/4Gu9J1FYrltAGakG2YT","1b4NBvVj5HTZIRnvffi3ao","3e70xqIkRNRZjvYOKglkEA","b9jx/3WRtNU7iR49+bVzFM","5e5hWQPlxHQ6vWH2K/qucW","441Yuq+LdG9qklZwRXP9hZ","bd2kQTRqVKfal6ZbyBsPDT","d5/Wz2AGZPcrXp8Y6PtQCB","acUACvFXlNZ6IgBvtWM+BT","c5H5tNSAlM/5o3Vpbbhu/g","d153KiJVFJmaO1IpyeqvG7","61S7jwnvhAi6DbdBtq4kn0","8aTCzbSwtJS5tuFrHJBjRH","2dq0K/rYRIHqPITxP87UNA","dfgSSsAVJJIbSKY3YQOaUF","58HV+4YfhN2KaWFjwKpmJB","a2DulkDrFCbpmgpyLxubJE","82I2UZzHBNvbANzfZimhNa","55bvU/DVFEF4bIZsIsBENZ","39Yf9bmslNYJzcR032dhi1","2dg9346xRKcL76H0P0i26G","22i11AZL5Oa5X1VoReSUis","75KGrreW9HmYN142dTbUGf","a3/OvxK/FE7b6OIXee+qJV","c0AKgMcwFPD75DMH6/AR2/","3bI76OLYROyI/prikWRRKi","629cEWt2FHT4pPkBqsutGI","e92i4sKxlKfLbfsWRLGLew","514IkKLPFERIVTnWZzO9nl","7e9BD/AL5GBKYHrxFyyllN","6e/zmdlYZMIKOyT+5pQKIR","c73FMy90NLjK5d9Z8E3GeE","c9xBU9BClH17b0CQDkE6F2","f3q7C07AFIvKaKwYHFXqhf","40UzqYWT1Lk6Ybb2AY9M1D","d3FdTLZ/VNC4IK3OWGxljP","07RcMdk+dIgJ3smov3qQn8","b7sDm5QTpJfqmfLiwAhzDg","4cabQjmXtIraW5Hb2nB1yg","85xTXCq7VDV6jLhJtq7kyG","01fgZg4XJExpUZTaAWNJHw","edAcAu7SRPW7tsadVxCRaV","28bkfczJVAUL/ljRzxJIVe","f4Q5KEKchLXp5ckA7lTxeE","dc8TT0i2RKIILzMu/eMtXc","59teFo3KFIEqJqhjF5ipxm","66NorxCGRJi788i0pNhacX","e4q+6EFjpAS6uPev7fCwzA","83D20seAVMD7GKRlVVglwp","52OPlKmk5LKbAYfFPDq2RG","22/LzSb45FQ7ME8DFUdxQk","dd5tHXXtVDPZiwXD3pWn6W","21cPUgR3JBGYp/epWyCeoT","775gQlFMVO95qeinWXR5R0","1006uYhA5J1aeyg0260xki","3aY56DAspCJJpDzSLU0JHJ","e2Rr75E1pA6Itqtbz/Rm03","50s3EPvKdOdLUNMV06ZChj","00obhPAfRIV6SaY+fozJlX","84eeREN0FCuanxhmDrT8bf","8106PGqJVPYrxbRe9X9hMD","b0czAFkG5CY5RBcYu0Mymp","7eRkdGaxtPSYnv0Q3HHNIu","943gNMfrpG/JPow41tJjUo","d48D558spG9rcOMwNkUbQW","9bTQau/sdKuLBDr7n4x/Er","afVhsJYVhJ1rRIk49+4gcS","f40EaM/PxEgrspMYxrcU7o","68fbTFseJA0KwS0aO/N1qk","383PrsZD1Iw6VtNBtMBnGA","772fC87pRJPbxFdOfiC3g1","5cq0qoAuhMZ5F6xAqhX/iA","4d3h89uG1K7YcWpvSaaV2i","e8Ueib+qJEhL6mXAHdnwbi","b4P/PCArtIdIH38t6mlw8Y","71VhFCTINJM6/Ky3oX9nBT","cf73jxyN9Jt47QTJU6ziYh","99FwsL0hBG8bITfZ4/IwmK","ecpdLyjvZBwrvm+cedCcQy","f0BIwQ8D5Ml7nTNQbh1YlS","e97GVMl6JHh5Ml5qEDdSGa","29FYIk+N1GYaeWH/q1NxQO","a2MjXRFdtLlYQ5ouAFv/+R","675ovJ2tVK2aLYfgPUWOMv","8855/VlrRKd6H0MSRnFxAU","7a/QZLET9IDreTiBfRn2PD","3ae7efMv1CLq2ilvUY/tQi","02delMVqdBD70a/HSD99FK"],"scenes":{"db://assets/ShuShiCrab/MainBuild.fire":69,"db://assets/ShuShiCrab/scene/main.fire":70},"redirect":[162,0,169,0,170,0,171,0],"deps":["internal"],"packs":{"0be78dc84":[79,165,103,8,102,2,99,3,7,6,98,4,1,164,70,163,5],"080b68abb":[85,104,73,118,89,81,82,95,96,87,90,80,94,91],"042d529df":[75,109,112,114,113,100,108],"017db4693":[76,110,115,111],"0be1f6f01":[105,86,167,168,74,83,92],"019e49d8a":[106,107],"0132d0cfe":[124,77,126,123,121,128],"02cb236a2":[78,119],"07d3be74e":[49,31,54,13,28,30,67,62,20,26,15,65,35,36,24,17,29,51,37,60,34,56,48,40,18,10,39,27,64,22,59,21,159,12,33,32,19,63,44,14,161,50,46,16,66,43,158,52,23,57,53,9,41,61,42,68,160,25,45,157,58,11,47,55,38]},"name":"ShuShiCrab","importBase":"import","nativeBase":"native","debug":false,"isZip":false,"encrypted":false,"versions":{"import":[142,"77a80","0132d0cfe","24d26","017db4693","3d839","019e49d8a","5a344","02cb236a2","48cc5","042d529df","8f075",120,"36910","07d3be74e","4524a","080b68abb","d1f84","0be1f6f01","948bc","0be78dc84","aa6cd",138,"3506e",136,"479dd",134,"3a2ca",71,"5dc7c",97,"650a0",153,"833de",139,"90334",122,"b59b9",156,"670c8",141,"fb249",133,"f4291",129,"4786f",155,"895d8",88,"a4990",130,"212b8",84,"0aa20",152,"e5e3d",154,"dfd54",137,"a76a1",146,"e3052",144,"88569",101,"be1b4",132,"1986f",143,"1e8e9",147,"18396",149,"58d97",166,"43d76",150,"6d38f",145,"48287",93,"fe3ce",116,"03e05",148,"a4b86",135,"89cee",140,"fa136",72,"e6ce7",131,"c567f",0,"c749c",125,"ef585",117,"eef97",127,"38e28",151,"23ff2",69,"e0feb"],"native":[49,"dc677",31,"a3ae3",54,"40656",13,"d4eb7",28,"547dc",30,"f8969",67,"6b44e",62,"21953",20,"5393f",26,"e4c13",15,"5b6f4",65,"2c114",35,"ad30f",36,"3b678",24,"4d085",17,"a049e",29,"e973e",51,"6d9a6",37,"7287e",60,"dc467",34,"1ee1b",56,"f9133",8,"44d86",48,"ea84d",40,"6fabd",18,"280ae",10,"accc5",2,"8c83e",39,"0f97a",27,"03f5f",64,"c52ec",22,"10536",59,"940bf",21,"1d71a",159,"c06a9",12,"85ec3",3,"11436",7,"becf3",33,"b03ef",32,"8ac2d",19,"6af27",63,"87da2",44,"4f07c",14,"c24e0",161,"d1118",50,"461ff",46,"9c479",16,"c972b",66,"4c01a",6,"6fdc7",43,"c6885",158,"83fcc",52,"9396b",23,"9a308",57,"e0c12",53,"98e1a",9,"e088c",41,"dabe3",61,"c2b07",42,"05d54",68,"d3d04",160,"a4b59",25,"62e7a",45,"3386c",4,"30bc7",1,"5f63b",157,"90cf4",58,"64ccf",11,"357f3",0,"d149b",47,"7a1eb",55,"fe76c",5,"ac31a",38,"9d471"]}}